{
  "posts": [
    {
      "id": 0,
      "title": "Atlanta",
      "text": "Two cousins, with different views on art versus commerce, on their way up through the Atlanta rap scene; \"Earnest 'Earn' Marks,\" an ambitious college drop-out and his estranged cousin, who suddenly becomes a star.",
      "image": {
        "src": "a.jpg",
        "alt": "Atlanta"
      }
    },
    {
      "id": 1,
      "title": "Billions",
      "text": "U.S. Attorney Chuck Rhoades goes after hedge fund king, Bobby \"Axe\" Axelrod in a battle between two powerful New York figures.",
      "image": {
        "src": "b.jpg",
        "alt": "Billions"
      }
    },
    {
      "id": 2,
      "title": "Black Mirror",
      "text": "A television anthology series that shows the dark side of life and technology.",
      "image": {
        "src": "bm.jpg",
        "alt": "Billions"
      }
    },
    {
      "id": 3,
      "title": "Atlanta",
      "text": "Two cousins, with different views on art versus commerce, on their way up through the Atlanta rap scene; \"Earnest 'Earn' Marks,\" an ambitious college drop-out and his estranged cousin, who suddenly becomes a star.",
      "image": {
        "src": "a.jpg",
        "alt": "Atlanta"
      }
    },
    {
      "id": 4,
      "title": "Billions",
      "text": "U.S. Attorney Chuck Rhoades goes after hedge fund king, Bobby \"Axe\" Axelrod in a battle between two powerful New York figures.",
      "image": {
        "src": "b.jpg",
        "alt": "Billions"
      }
    },
    {
      "id": 5,
      "title": "Black Mirror",
      "text": "A television anthology series that shows the dark side of life and technology.",
      "image": {
        "src": "bm.jpg",
        "alt": "Billions"
      }
    }
  ]
}
